scalexi/__init__.py
scalexi/data/__init__.py
scalexi/data/openai_pricing.json
scalexi/data/openai_pricing_v1.json
scalexi/data/openai_pricing_v2.json
scalexi/dataset_generation/__init__.py
scalexi/dataset_generation/prompt_completion.py
scalexi/document_loaders/__init__.py
scalexi/document_loaders/context_loaders.py
scalexi/document_loaders/pdf_loader.py
scalexi/document_loaders/pdf_loaders_v1.py
scalexi/generators/__init__.py
scalexi/generators/generator.py
scalexi/llm/__init__.py
scalexi/llm/google_gemini.py
scalexi/llm/openai_gpt.py
scalexi/llm_evaluation/__init__.py
scalexi/llm_evaluation/evaluate.py
scalexi/openai/__init__.py
scalexi/openai/fine_tuning_api.py
scalexi/openai/pricing.py
scalexi/openai/utilities.py
scalexi/rag/__init__.py
scalexi/rag/vectorestores.py
scalexi/rag/vectorstores.py
scalexi/rag/config/__init__.py
scalexi/rag/data/__init__.py
scalexi/utilities/__init__.py
scalexi/utilities/api.py
scalexi/utilities/data_formatter.py
scalexi/utilities/logger.py
scalexi/utilities/text_processing.py
scalexi-0.5.5.dist-info/LICENSE
scalexi-0.5.5.dist-info/METADATA
scalexi-0.5.5.dist-info/WHEEL
scalexi-0.5.5.dist-info/top_level.txt
scalexi-0.5.5.dist-info/RECORD
