Metadata-Version: 2.1
Name: scalexi
Version: 0.5.5
Summary: The scalexi package is a versatile open-source Python library that focuses on facilitating low-code development and fine-tuning of diverse Large Language Models (LLMs). It extends beyond its initial OpenAI models integration, offering a scalable framework for various LLMs.
Home-page: https://github.com/scalexi/scalexi
Author: ScaleX Innovation
Author-email: akoubaa@scalexi.ai
Classifier: License :: Other/Proprietary License
Classifier: Programming Language :: Python :: 3.11
License-File: LICENSE
Requires-Dist: pandas
Requires-Dist: openai
Requires-Dist: sphinx
Requires-Dist: cohere
Requires-Dist: sphinx-rtd-theme
Requires-Dist: tiktoken
Requires-Dist: pyyaml
Requires-Dist: lxml
Requires-Dist: requests
Requires-Dist: httpx==0.27.0
Requires-Dist: langchain
Requires-Dist: langchain-openai
Requires-Dist: langchain-core
Requires-Dist: pypdf
Requires-Dist: fastapi
Requires-Dist: pymupdf
Requires-Dist: faiss-cpu
Requires-Dist: langchain-text-splitters
Requires-Dist: chromadb
Requires-Dist: anthropic
Requires-Dist: langchain-community
Requires-Dist: aiofiles
Requires-Dist: asyncio
Requires-Dist: aiohttp
Requires-Dist: pdfplumber
Requires-Dist: PyPDF2
Requires-Dist: pyautogen
Requires-Dist: chardet
Requires-Dist: pycryptodome
Requires-Dist: seaborn
Requires-Dist: matplotlib
Requires-Dist: scipy
Requires-Dist: pygments
Requires-Dist: langchain-chroma
Requires-Dist: langchain-experimental
Requires-Dist: langgraph
